Metadata-Version: 2.1
Name: cp-sentry-dingding
Version: 1.0.5
Summary: A Sentry extension which send errors stats to DingDing
Home-page: https://github.com/cench/sentry-10-dingding
Author: season
Author-email: season2991@gmail.com
License: MIT
Keywords: sentry dingding
Platform: UNKNOWN
Classifier: Programming Language :: Python :: 2.7
Classifier: License :: OSI Approved :: MIT License
